{
  "date": "2026-06-24",
  "source_csv": "move_pattern_5d_today.csv",
  "summary": {
    "总条目": 5,
    "可开仓": 0,
    "观望": 5
  },
  "rows": [
    {
      "代码": "ARM",
      "方向": "偏多",
      "规律": "5日内涨≥2% · 量比≥1.5 · 5日涨≥20% · 收强≥55% · 换手≥1.0% · dvol≥$100M · MA50+MA20",
      "5日命中率": 0.8185,
      "样本数": 270,
      "阈值%": 2.0,
      "建议": "5日内路径达标 → 做多（寻优）",
      "量比": 1.76,
      "5日涨跌%": 30.5,
      "成交额M": 6500.4,
      "换手率%": 2.05
    },
    {
      "代码": "IBM",
      "方向": "偏多",
      "规律": "5日内涨≥3% · 量比>2.5 · 5日涨幅>15% · 成交额>1B · MA50上",
      "5日命中率": 0.7679,
      "样本数": 112,
      "阈值%": 3.0,
      "建议": "5日内路径达标 → 做多",
      "量比": 3.63,
      "5日涨跌%": 15.8,
      "成交额M": 6503.3,
      "换手率%": 2.74
    },
    {
      "代码": "INTU",
      "方向": "偏空",
      "规律": "5日内跌≥2% · 量比≥2.0 · 5日跌≤-10% · 收弱≤45% · 换手≥1.0% · 全趋势",
      "5日命中率": 0.7598,
      "样本数": 383,
      "阈值%": 2.0,
      "建议": "5日内路径达标 → 回避（寻优）",
      "量比": 6.08,
      "5日涨跌%": -18.8,
      "成交额M": 6864.1,
      "换手率%": 8.17
    },
    {
      "代码": "NIO",
      "方向": "偏空",
      "规律": "5日内跌≥2% · 量比≥2.0 · 5日跌≤-10% · 收弱≤45% · 换手≥1.0% · 全趋势",
      "5日命中率": 0.7598,
      "样本数": 383,
      "阈值%": 2.0,
      "建议": "5日内路径达标 → 回避（寻优）",
      "量比": 2.9,
      "5日涨跌%": -10.4,
      "成交额M": 566.3,
      "换手率%": 4.04
    },
    {
      "代码": "REGN",
      "方向": "偏空",
      "规律": "5日内跌≥3% · 量比1.0-1.5 · 5日跌幅<-5% · 成交额200M-1B · MA50下",
      "5日命中率": 0.6113,
      "样本数": 1711,
      "阈值%": 3.0,
      "建议": "5日内路径达标 → 回避",
      "量比": 1.17,
      "5日涨跌%": -9.7,
      "成交额M": 757.3,
      "换手率%": 1.12
    }
  ],
  "picks": [
    {
      "代码": "ARM",
      "方向": "偏多",
      "规律": "5日内涨≥2% · 量比≥1.5 · 5日涨≥20% · 收强≥55% · 换手≥1.0% · dvol≥$100M · MA50+MA20",
      "5日命中率": 0.8185,
      "样本数": 270,
      "阈值%": 2.0,
      "建议": "5日内路径达标 → 做多（寻优）",
      "量比": 1.76,
      "5日涨跌%": 30.5,
      "成交额M": 6500.4,
      "换手率%": 2.05
    },
    {
      "代码": "IBM",
      "方向": "偏多",
      "规律": "5日内涨≥3% · 量比>2.5 · 5日涨幅>15% · 成交额>1B · MA50上",
      "5日命中率": 0.7679,
      "样本数": 112,
      "阈值%": 3.0,
      "建议": "5日内路径达标 → 做多",
      "量比": 3.63,
      "5日涨跌%": 15.8,
      "成交额M": 6503.3,
      "换手率%": 2.74
    },
    {
      "代码": "INTU",
      "方向": "偏空",
      "规律": "5日内跌≥2% · 量比≥2.0 · 5日跌≤-10% · 收弱≤45% · 换手≥1.0% · 全趋势",
      "5日命中率": 0.7598,
      "样本数": 383,
      "阈值%": 2.0,
      "建议": "5日内路径达标 → 回避（寻优）",
      "量比": 6.08,
      "5日涨跌%": -18.8,
      "成交额M": 6864.1,
      "换手率%": 8.17
    },
    {
      "代码": "NIO",
      "方向": "偏空",
      "规律": "5日内跌≥2% · 量比≥2.0 · 5日跌≤-10% · 收弱≤45% · 换手≥1.0% · 全趋势",
      "5日命中率": 0.7598,
      "样本数": 383,
      "阈值%": 2.0,
      "建议": "5日内路径达标 → 回避（寻优）",
      "量比": 2.9,
      "5日涨跌%": -10.4,
      "成交额M": 566.3,
      "换手率%": 4.04
    },
    {
      "代码": "REGN",
      "方向": "偏空",
      "规律": "5日内跌≥3% · 量比1.0-1.5 · 5日跌幅<-5% · 成交额200M-1B · MA50下",
      "5日命中率": 0.6113,
      "样本数": 1711,
      "阈值%": 3.0,
      "建议": "5日内路径达标 → 回避",
      "量比": 1.17,
      "5日涨跌%": -9.7,
      "成交额M": 757.3,
      "换手率%": 1.12
    }
  ]
}
